Workbook

Sheet Portfolio Summary
A1: MRS Oil Annual General Meeting Travel Program — Nairobi, Kenya | B1: MRS Oil Annual General Meeting Travel Program — Nairobi, Kenya | C1: MRS Oil Annual General Meeting Travel Program — Nairobi, Kenya | D1: MRS Oil Annual General Meeting Travel Program — Nairobi, Kenya | E1: MRS Oil Annual General Meeting Travel Program — Nairobi, Kenya | F1: MRS Oil Annual General Meeting Travel Program — Nairobi, Kenya | G1: MRS Oil Annual General Meeting Travel Program — Nairobi, Kenya | H1: MRS Oil Annual General Meeting Travel Program — Nairobi, Kenya
A2: MRS Oil Annual General Meeting Travel Program — Nairobi, Kenya | B2: MRS Oil Annual General Meeting Travel Program — Nairobi, Kenya | C2: MRS Oil Annual General Meeting Travel Program — Nairobi, Kenya | D2: MRS Oil Annual General Meeting Travel Program — Nairobi, Kenya | E2: MRS Oil Annual General Meeting Travel Program — Nairobi, Kenya | F2: MRS Oil Annual General Meeting Travel Program — Nairobi, Kenya | G2: MRS Oil Annual General Meeting Travel Program — Nairobi, Kenya | H2: MRS Oil Annual General Meeting Travel Program — Nairobi, Kenya
A3: Project period: Feb 2020–Mar 2021 | Role: Account Manager / Project Lead | 180 travelers | 5 days / 4 nights | B3: Project period: Feb 2020–Mar 2021 | Role: Account Manager / Project Lead | 180 travelers | 5 days / 4 nights | C3: Project period: Feb 2020–Mar 2021 | Role: Account Manager / Project Lead | 180 travelers | 5 days / 4 nights | D3: Project period: Feb 2020–Mar 2021 | Role: Account Manager / Project Lead | 180 travelers | 5 days / 4 nights | E3: Project period: Feb 2020–Mar 2021 | Role: Account Manager / Project Lead | 180 travelers | 5 days / 4 nights | F3: Project period: Feb 2020–Mar 2021 | Role: Account Manager / Project Lead | 180 travelers | 5 days / 4 nights | G3: Project period: Feb 2020–Mar 2021 | Role: Account Manager / Project Lead | 180 travelers | 5 days / 4 nights | H3: Project period: Feb 2020–Mar 2021 | Role: Account Manager / Project Lead | 180 travelers | 5 days / 4 nights
A5: Business context | B5: Finchglow Travels coordinated an international annual general meeting travel program for MRS Oil employees and executives. | D5: SUCCESS CRITERIA | E5: SUCCESS CRITERIA | F5: SUCCESS CRITERIA | G5: SUCCESS CRITERIA | H5: SUCCESS CRITERIA
A6: Project objective | B6: Plan and execute end-to-end travel, accommodation, conference, ground transport, leisure and traveler-support services in Nairobi. | D6: 1. All travelers ticketed, documented and briefed before departure
A7: Complexity | B7: 180 travelers; cross-functional delivery; multiple Kenyan vendors; credit constraints; evolving COVID-19 entry, testing, capacity and safety requirements. | D7: 2. Conference, hotel, transport and leisure vendors contracted and confirmed
A8: My responsibilities | B8: Requirements gathering, stakeholder coordination, schedule, vendor management, budget control, credit negotiation, risk planning, traveler communications and execution oversight. | D8: 3. Revised spending maintained within the approved ₦165 million ceiling
A9: Original budget | B9: ₦132.0 million — illustrative pre-COVID baseline. | D9: 4. Health, medical, evacuation and supplier-failure contingencies activated
A10: Revised budget | B10: ₦165.0 million after a 25% COVID-era rebaseline. | D10: 5. Daily movements delivered safely with rapid incident escalation
A11: Actual spend | B11: ₦160.5 million — ₦4.5 million below revised budget. | D11: 6. Program closed with reconciled invoices, feedback and lessons learned
A12: Execution | B12: Five-day/four-night Nairobi program delivered in March 2021 with conference sessions, local movements, group activities and medical standby.
A13: Illustrative outcome | B13: 180 travelers supported; 100% manifest reconciliation; 96% on-time movements; 92% satisfaction; no major safety incidents.

Sheet Project Timeline
A1: Fourteen-Month Project Timeline & COVID-19 Rebaseline | B1: Fourteen-Month Project Timeline & COVID-19 Rebaseline | C1: Fourteen-Month Project Timeline & COVID-19 Rebaseline | D1: Fourteen-Month Project Timeline & COVID-19 Rebaseline | E1: Fourteen-Month Project Timeline & COVID-19 Rebaseline | F1: Fourteen-Month Project Timeline & COVID-19 Rebaseline | G1: Fourteen-Month Project Timeline & COVID-19 Rebaseline | H1: Fourteen-Month Project Timeline & COVID-19 Rebaseline | I1: Fourteen-Month Project Timeline & COVID-19 Rebaseline | J1: Fourteen-Month Project Timeline & COVID-19 Rebaseline | K1: Fourteen-Month Project Timeline & COVID-19 Rebaseline | L1: Fourteen-Month Project Timeline & COVID-19 Rebaseline | M1: Fourteen-Month Project Timeline & COVID-19 Rebaseline | N1: Fourteen-Month Project Timeline & COVID-19 Rebaseline | O1: Fourteen-Month Project Timeline & COVID-19 Rebaseline | P1: Fourteen-Month Project Timeline & COVID-19 Rebaseline | Q1: Fourteen-Month Project Timeline & COVID-19 Rebaseline | R1: Fourteen-Month Project Timeline & COVID-19 Rebaseline | S1: Fourteen-Month Project Timeline & COVID-19 Rebaseline | T1: Fourteen-Month Project Timeline & COVID-19 Rebaseline | U1: Fourteen-Month Project Timeline & COVID-19 Rebaseline
A2: Fourteen-Month Project Timeline & COVID-19 Rebaseline | B2: Fourteen-Month Project Timeline & COVID-19 Rebaseline | C2: Fourteen-Month Project Timeline & COVID-19 Rebaseline | D2: Fourteen-Month Project Timeline & COVID-19 Rebaseline | E2: Fourteen-Month Project Timeline & COVID-19 Rebaseline | F2: Fourteen-Month Project Timeline & COVID-19 Rebaseline | G2: Fourteen-Month Project Timeline & COVID-19 Rebaseline | H2: Fourteen-Month Project Timeline & COVID-19 Rebaseline | I2: Fourteen-Month Project Timeline & COVID-19 Rebaseline | J2: Fourteen-Month Project Timeline & COVID-19 Rebaseline | K2: Fourteen-Month Project Timeline & COVID-19 Rebaseline | L2: Fourteen-Month Project Timeline & COVID-19 Rebaseline | M2: Fourteen-Month Project Timeline & COVID-19 Rebaseline | N2: Fourteen-Month Project Timeline & COVID-19 Rebaseline | O2: Fourteen-Month Project Timeline & COVID-19 Rebaseline | P2: Fourteen-Month Project Timeline & COVID-19 Rebaseline | Q2: Fourteen-Month Project Timeline & COVID-19 Rebaseline | R2: Fourteen-Month Project Timeline & COVID-19 Rebaseline | S2: Fourteen-Month Project Timeline & COVID-19 Rebaseline | T2: Fourteen-Month Project Timeline & COVID-19 Rebaseline | U2: Fourteen-Month Project Timeline & COVID-19 Rebaseline
A3: Blue bars show the planning window. The December 2020 rebaseline incorporated new health, supplier and contingency requirements. | B3: Blue bars show the planning window. The December 2020 rebaseline incorporated new health, supplier and contingency requirements. | C3: Blue bars show the planning window. The December 2020 rebaseline incorporated new health, supplier and contingency requirements. | D3: Blue bars show the planning window. The December 2020 rebaseline incorporated new health, supplier and contingency requirements. | E3: Blue bars show the planning window. The December 2020 rebaseline incorporated new health, supplier and contingency requirements. | F3: Blue bars show the planning window. The December 2020 rebaseline incorporated new health, supplier and contingency requirements. | G3: Blue bars show the planning window. The December 2020 rebaseline incorporated new health, supplier and contingency requirements. | H3: Blue bars show the planning window. The December 2020 rebaseline incorporated new health, supplier and contingency requirements. | I3: Blue bars show the planning window. The December 2020 rebaseline incorporated new health, supplier and contingency requirements. | J3: Blue bars show the planning window. The December 2020 rebaseline incorporated new health, supplier and contingency requirements. | K3: Blue bars show the planning window. The December 2020 rebaseline incorporated new health, supplier and contingency requirements. | L3: Blue bars show the planning window. The December 2020 rebaseline incorporated new health, supplier and contingency requirements. | M3: Blue bars show the planning window. The December 2020 rebaseline incorporated new health, supplier and contingency requirements. | N3: Blue bars show the planning window. The December 2020 rebaseline incorporated new health, supplier and contingency requirements. | O3: Blue bars show the planning window. The December 2020 rebaseline incorporated new health, supplier and contingency requirements. | P3: Blue bars show the planning window. The December 2020 rebaseline incorporated new health, supplier and contingency requirements. | Q3: Blue bars show the planning window. The December 2020 rebaseline incorporated new health, supplier and contingency requirements. | R3: Blue bars show the planning window. The December 2020 rebaseline incorporated new health, supplier and contingency requirements. | S3: Blue bars show the planning window. The December 2020 rebaseline incorporated new health, supplier and contingency requirements. | T3: Blue bars show the planning window. The December 2020 rebaseline incorporated new health, supplier and contingency requirements. | U3: Blue bars show the planning window. The December 2020 rebaseline incorporated new health, supplier and contingency requirements.
A4: Workstream | B4: Activity | C4: Start | D4: Finish | E4: Owner | F4: Deliverable | G4: Feb-20 | H4: Mar-20 | I4: Apr-20 | J4: May-20 | K4: Jun-20 | L4: Jul-20 | M4: Aug-20 | N4: Sep-20 | O4: Oct-20 | P4: Nov-20 | Q4: Dec-20 | R4: Jan-21 | S4: Feb-21 | T4: Mar-21 | U4: Status
A5: Initiation | B5: Prior-trip review, charter and requirements | C5: 43864 | D5: 43889 | E5: Account Manager | F5: Approved charter | G5: =IF(AND($C5<=G$23,$D5>=G$22),1,"") -> 1 | H5: =IF(AND($C5<=H$23,$D5>=H$22),1,"") | I5: =IF(AND($C5<=I$23,$D5>=I$22),1,"") | J5: =IF(AND($C5<=J$23,$D5>=J$22),1,"") | K5: =IF(AND($C5<=K$23,$D5>=K$22),1,"") | L5: =IF(AND($C5<=L$23,$D5>=L$22),1,"") | M5: =IF(AND($C5<=M$23,$D5>=M$22),1,"") | N5: =IF(AND($C5<=N$23,$D5>=N$22),1,"") | ... T5: =IF(AND($C5<=T$23,$D5>=T$22),1,"") | U5: Complete
A6: Planning | B6: Destination options and feasibility | C6: 43878 | D6: 43910 | E6: Account Manager | F6: Nairobi recommendation | G6: =IF(AND($C6<=G$23,$D6>=G$22),1,"") -> 1 | H6: =IF(AND($C6<=H$23,$D6>=H$22),1,"") -> 1 | I6: =IF(AND($C6<=I$23,$D6>=I$22),1,"") | J6: =IF(AND($C6<=J$23,$D6>=J$22),1,"") | K6: =IF(AND($C6<=K$23,$D6>=K$22),1,"") | L6: =IF(AND($C6<=L$23,$D6>=L$22),1,"") | M6: =IF(AND($C6<=M$23,$D6>=M$22),1,"") | N6: =IF(AND($C6<=N$23,$D6>=N$22),1,"") | ... T6: =IF(AND($C6<=T$23,$D6>=T$22),1,"") | U6: Complete
A7: Disruption | B7: COVID impact assessment and planning pause | C7: 43906 | D7: 43951 | E7: Project Team | F7: Impact assessment | G7: =IF(AND($C7<=G$23,$D7>=G$22),1,"") | H7: =IF(AND($C7<=H$23,$D7>=H$22),1,"") -> 1 | I7: =IF(AND($C7<=I$23,$D7>=I$22),1,"") -> 1 | J7: =IF(AND($C7<=J$23,$D7>=J$22),1,"") | K7: =IF(AND($C7<=K$23,$D7>=K$22),1,"") | L7: =IF(AND($C7<=L$23,$D7>=L$22),1,"") | M7: =IF(AND($C7<=M$23,$D7>=M$22),1,"") | N7: =IF(AND($C7<=N$23,$D7>=N$22),1,"") | ... T7: =IF(AND($C7<=T$23,$D7>=T$22),1,"") | U7: Complete
A8: Sourcing | B8: Flights, hotel and venue RFP | C8: 43955 | D8: 44008 | E8: Travel/Holidays | F8: Vendor options | G8: =IF(AND($C8<=G$23,$D8>=G$22),1,"") | H8: =IF(AND($C8<=H$23,$D8>=H$22),1,"") | I8: =IF(AND($C8<=I$23,$D8>=I$22),1,"") | J8: =IF(AND($C8<=J$23,$D8>=J$22),1,"") -> 1 | K8: =IF(AND($C8<=K$23,$D8>=K$22),1,"") -> 1 | L8: =IF(AND($C8<=L$23,$D8>=L$22),1,"") | M8: =IF(AND($C8<=M$23,$D8>=M$22),1,"") | N8: =IF(AND($C8<=N$23,$D8>=N$22),1,"") | ... T8: =IF(AND($C8<=T$23,$D8>=T$22),1,"") | U8: Complete
A9: Design | B9: Draft itinerary and event program | C9: 43997 | D9: 44050 | E9: Account Manager | F9: Integrated itinerary | G9: =IF(AND($C9<=G$23,$D9>=G$22),1,"") | H9: =IF(AND($C9<=H$23,$D9>=H$22),1,"") | I9: =IF(AND($C9<=I$23,$D9>=I$22),1,"") | J9: =IF(AND($C9<=J$23,$D9>=J$22),1,"") | K9: =IF(AND($C9<=K$23,$D9>=K$22),1,"") -> 1 | L9: =IF(AND($C9<=L$23,$D9>=L$22),1,"") -> 1 | M9: =IF(AND($C9<=M$23,$D9>=M$22),1,"") -> 1 | N9: =IF(AND($C9<=N$23,$D9>=N$22),1,"") | ... T9: =IF(AND($C9<=T$23,$D9>=T$22),1,"") | U9: Complete
A10: Contracting | B10: Hotel, transport and venue contracting | C10: 44046 | D10: 44120 | E10: Procurement/Legal | F10: Signed agreements | G10: =IF(AND($C10<=G$23,$D10>=G$22),1,"") | H10: =IF(AND($C10<=H$23,$D10>=H$22),1,"") | I10: =IF(AND($C10<=I$23,$D10>=I$22),1,"") | J10: =IF(AND($C10<=J$23,$D10>=J$22),1,"") | K10: =IF(AND($C10<=K$23,$D10>=K$22),1,"") | L10: =IF(AND($C10<=L$23,$D10>=L$22),1,"") | M10: =IF(AND($C10<=M$23,$D10>=M$22),1,"") -> 1 | N10: =IF(AND($C10<=N$23,$D10>=N$22),1,"") -> 1 | ... T10: =IF(AND($C10<=T$23,$D10>=T$22),1,"") | U10: Complete
A11: Finance | B11: Credit structure and deposit schedule | C11: 44075 | D11: 44148 | E11: Finance/Account Manager | F11: Funding plan | G11: =IF(AND($C11<=G$23,$D11>=G$22),1,"") | H11: =IF(AND($C11<=H$23,$D11>=H$22),1,"") | I11: =IF(AND($C11<=I$23,$D11>=I$22),1,"") | J11: =IF(AND($C11<=J$23,$D11>=J$22),1,"") | K11: =IF(AND($C11<=K$23,$D11>=K$22),1,"") | L11: =IF(AND($C11<=L$23,$D11>=L$22),1,"") | M11: =IF(AND($C11<=M$23,$D11>=M$22),1,"") | N11: =IF(AND($C11<=N$23,$D11>=N$22),1,"") -> 1 | ... T11: =IF(AND($C11<=T$23,$D11>=T$22),1,"") | U11: Complete
A12: Rebaseline | B12: COVID requirements, budget and schedule reset | C12: 44137 | D12: 44183 | E12: Account Manager | F12: Approved rebaseline | G12: =IF(AND($C12<=G$23,$D12>=G$22),1,"") | H12: =IF(AND($C12<=H$23,$D12>=H$22),1,"") | I12: =IF(AND($C12<=I$23,$D12>=I$22),1,"") | J12: =IF(AND($C12<=J$23,$D12>=J$22),1,"") | K12: =IF(AND($C12<=K$23,$D12>=K$22),1,"") | L12: =IF(AND($C12<=L$23,$D12>=L$22),1,"") | M12: =IF(AND($C12<=M$23,$D12>=M$22),1,"") | N12: =IF(AND($C12<=N$23,$D12>=N$22),1,"") | ... T12: =IF(AND($C12<=T$23,$D12>=T$22),1,"") | U12: Complete
A13: Risk | B13: Medical, evacuation and contingency plan | C13: 44166 | D13: 44225 | E13: Risk/Medical | F13: Emergency plan | G13: =IF(AND($C13<=G$23,$D13>=G$22),1,"") | H13: =IF(AND($C13<=H$23,$D13>=H$22),1,"") | I13: =IF(AND($C13<=I$23,$D13>=I$22),1,"") | J13: =IF(AND($C13<=J$23,$D13>=J$22),1,"") | K13: =IF(AND($C13<=K$23,$D13>=K$22),1,"") | L13: =IF(AND($C13<=L$23,$D13>=L$22),1,"") | M13: =IF(AND($C13<=M$23,$D13>=M$22),1,"") | N13: =IF(AND($C13<=N$23,$D13>=N$22),1,"") | ... T13: =IF(AND($C13<=T$23,$D13>=T$22),1,"") | U13: Complete
A14: Readiness | B14: Traveler data, documents and health readiness | C14: 44200 | D14: 44253 | E14: Travel Team | F14: Cleared traveler list | G14: =IF(AND($C14<=G$23,$D14>=G$22),1,"") | H14: =IF(AND($C14<=H$23,$D14>=H$22),1,"") | I14: =IF(AND($C14<=I$23,$D14>=I$22),1,"") | J14: =IF(AND($C14<=J$23,$D14>=J$22),1,"") | K14: =IF(AND($C14<=K$23,$D14>=K$22),1,"") | L14: =IF(AND($C14<=L$23,$D14>=L$22),1,"") | M14: =IF(AND($C14<=M$23,$D14>=M$22),1,"") | N14: =IF(AND($C14<=N$23,$D14>=N$22),1,"") | ... T14: =IF(AND($C14<=T$23,$D14>=T$22),1,"") | U14: Complete
A15: Comms | B15: Briefings, itinerary packs and help desk | C15: 44228 | D15: 44260 | E15: Account Manager | F15: Traveler packs | G15: =IF(AND($C15<=G$23,$D15>=G$22),1,"") | H15: =IF(AND($C15<=H$23,$D15>=H$22),1,"") | I15: =IF(AND($C15<=I$23,$D15>=I$22),1,"") | J15: =IF(AND($C15<=J$23,$D15>=J$22),1,"") | K15: =IF(AND($C15<=K$23,$D15>=K$22),1,"") | L15: =IF(AND($C15<=L$23,$D15>=L$22),1,"") | M15: =IF(AND($C15<=M$23,$D15>=M$22),1,"") | N15: =IF(AND($C15<=N$23,$D15>=N$22),1,"") | ... T15: =IF(AND($C15<=T$23,$D15>=T$22),1,"") -> 1 | U15: Complete
A16: Finalization | B16: Vendor confirmations and command-center test | C16: 44242 | D16: 44260 | E16: Project Team | F16: Go-live checklist | G16: =IF(AND($C16<=G$23,$D16>=G$22),1,"") | H16: =IF(AND($C16<=H$23,$D16>=H$22),1,"") | I16: =IF(AND($C16<=I$23,$D16>=I$22),1,"") | J16: =IF(AND($C16<=J$23,$D16>=J$22),1,"") | K16: =IF(AND($C16<=K$23,$D16>=K$22),1,"") | L16: =IF(AND($C16<=L$23,$D16>=L$22),1,"") | M16: =IF(AND($C16<=M$23,$D16>=M$22),1,"") | N16: =IF(AND($C16<=N$23,$D16>=N$22),1,"") | ... T16: =IF(AND($C16<=T$23,$D16>=T$22),1,"") -> 1 | U16: Complete
... A18: Closeout | B18: Invoice reconciliation and lessons learned | C18: 44270 | D18: 44286 | E18: Account Manager/Finance | F18: Closeout report | G18: =IF(AND($C18<=G$23,$D18>=G$22),1,"") | H18: =IF(AND($C18<=H$23,$D18>=H$22),1,"") | I18: =IF(AND($C18<=I$23,$D18>=I$22),1,"") | J18: =IF(AND($C18<=J$23,$D18>=J$22),1,"") | K18: =IF(AND($C18<=K$23,$D18>=K$22),1,"") | L18: =IF(AND($C18<=L$23,$D18>=L$22),1,"") | M18: =IF(AND($C18<=M$23,$D18>=M$22),1,"") | N18: =IF(AND($C18<=N$23,$D18>=N$22),1,"") | ... T18: =IF(AND($C18<=T$23,$D18>=T$22),1,"") -> 1 | U18: Complete
G22: 43862 | H22: 43891 | I22: 43922 | J22: 43952 | K22: 43983 | L22: 44013 | M22: 44044 | N22: 44075 | O22: 44105 | P22: 44136 | Q22: 44166 | R22: 44197 | S22: 44228 | T22: 44256
G23: 43890 | H23: 43921 | I23: 43951 | J23: 43982 | K23: 44012 | L23: 44043 | M23: 44074 | N23: 44104 | O23: 44135 | P23: 44165 | Q23: 44196 | R23: 44227 | S23: 44255 | T23: 44286

Sheet Budget Control
A1: Budget Control & COVID-19 Rebaseline — ₦ Millions | B1: Budget Control & COVID-19 Rebaseline — ₦ Millions | C1: Budget Control & COVID-19 Rebaseline — ₦ Millions | D1: Budget Control & COVID-19 Rebaseline — ₦ Millions | E1: Budget Control & COVID-19 Rebaseline — ₦ Millions | F1: Budget Control & COVID-19 Rebaseline — ₦ Millions | G1: Budget Control & COVID-19 Rebaseline — ₦ Millions | H1: Budget Control & COVID-19 Rebaseline — ₦ Millions
A2: Budget Control & COVID-19 Rebaseline — ₦ Millions | B2: Budget Control & COVID-19 Rebaseline — ₦ Millions | C2: Budget Control & COVID-19 Rebaseline — ₦ Millions | D2: Budget Control & COVID-19 Rebaseline — ₦ Millions | E2: Budget Control & COVID-19 Rebaseline — ₦ Millions | F2: Budget Control & COVID-19 Rebaseline — ₦ Millions | G2: Budget Control & COVID-19 Rebaseline — ₦ Millions | H2: Budget Control & COVID-19 Rebaseline — ₦ Millions
A3: Positive revised variance means actual spend was below the revised budget. | B3: All amounts are illustrative. Positive revised variance means actual spend was below the revised budget. | C3: All amounts are illustrative. Positive revised variance means actual spend was below the revised budget. | D3: All amounts are illustrative. Positive revised variance means actual spend was below the revised budget. | E3: All amounts are illustrative. Positive revised variance means actual spend was below the revised budget. | F3: All amounts are illustrative. Positive revised variance means actual spend was below the revised budget. | G3: All amounts are illustrative. Positive revised variance means actual spend was below the revised budget. | H3: All amounts are illustrative. Positive revised variance means actual spend was below the revised budget.
A5: Cost category | B5: Original budget | C5: Revised budget | D5: Actual spend | E5: Rebaseline increase | F5: Variance to revised | G5: Actual / revised | H5: Comment
A6: International flights | B6: 56 | C6: 66 | D6: 67.8 | E6: =C6-B6 -> 10 | F6: =C6-D6 -> -1.8 | G6: =D6/C6 -> 1.0272727 | H6: Higher fares and schedule flexibility
A7: Hotel accommodation | B7: 35 | C7: 41.25 | D7: 39.8 | E7: =C7-B7 -> 6.25 | F7: =C7-D7 -> 1.45 | G7: =D7/C7 -> 0.96484848 | H7: Flexible room block and health protocols
A8: Ground transportation | B8: 10 | C8: 13.2 | D8: 12.7 | E8: =C8-B8 -> 3.2 | F8: =C8-D8 -> 0.5 | G8: =D8/C8 -> 0.96212121 | H8: Additional vehicles and capacity controls
A9: Conference venue & AV | B9: 9 | C9: 11.55 | D9: 11.2 | E9: =C9-B9 -> 2.55 | F9: =C9-D9 -> 0.35 | G9: =D9/C9 -> 0.96969697 | H9: Spacing, equipment and revised event setup
A10: Group activities | B10: 8 | C10: 9.9 | D10: 9.5 | E10: =C10-B10 -> 1.9 | F10: =C10-D10 -> 0.4 | G10: =D10/C10 -> 0.95959596 | H10: Rescheduled and lower-density activities
A11: Health & safety | B11: 2 | C11: 8.25 | D11: 8.8 | E11: =C11-B11 -> 6.25 | F11: =C11-D11 -> -0.55 | G11: =D11/C11 -> 1.0666667 | H11: Testing, PPE, standby doctor and medical support
A12: Insurance, visa & admin | B12: 4 | C12: 4.95 | D12: 4.8 | E12: =C12-B12 -> 0.95 | F12: =C12-D12 -> 0.15 | G12: =D12/C12 -> 0.96969697 | H12: Expanded travel support and documentation
A13: Contingency reserve | B13: 8 | C13: 9.9 | D13: 5.9 | E13: =C13-B13 -> 1.9 | F13: =C13-D13 -> 4 | G13: =D13/C13 -> 0.5959596 | H13: Risk reserve partially consumed
A14: TOTAL | B14: =SUM(B6:B13) -> 132 | C14: =SUM(C6:C13) -> 165 | D14: =SUM(D6:D13) -> 160.5 | E14: =C14-B14 -> 33 | F14: =C14-D14 -> 4.5 | G14: =D14/C14 -> 0.97272727 | H14: Modeled closeout

Sheet Vendor Tracker
A1: Vendor & Contract Tracker | B1: Vendor & Contract Tracker | C1: Vendor & Contract Tracker | D1: Vendor & Contract Tracker | E1: Vendor & Contract Tracker | F1: Vendor & Contract Tracker | G1: Vendor & Contract Tracker | H1: Vendor & Contract Tracker | I1: Vendor & Contract Tracker | J1: Vendor & Contract Tracker
A2: Vendor & Contract Tracker | B2: Vendor & Contract Tracker | C2: Vendor & Contract Tracker | D2: Vendor & Contract Tracker | E2: Vendor & Contract Tracker | F2: Vendor & Contract Tracker | G2: Vendor & Contract Tracker | H2: Vendor & Contract Tracker | I2: Vendor & Contract Tracker | J2: Vendor & Contract Tracker
A3: Track critical commercial, operational and contingency commitments across Nigeria and Kenya. | B3: Track critical commercial, operational and contingency commitments across Nigeria and Kenya. | C3: Track critical commercial, operational and contingency commitments across Nigeria and Kenya. | D3: Track critical commercial, operational and contingency commitments across Nigeria and Kenya. | E3: Track critical commercial, operational and contingency commitments across Nigeria and Kenya. | F3: Track critical commercial, operational and contingency commitments across Nigeria and Kenya. | G3: Track critical commercial, operational and contingency commitments across Nigeria and Kenya. | H3: Track critical commercial, operational and contingency commitments across Nigeria and Kenya. | I3: Track critical commercial, operational and contingency commitments across Nigeria and Kenya. | J3: Track critical commercial, operational and contingency commitments across Nigeria and Kenya.
A4: Package | B4: Vendor type | C4: Location | D4: Contract value (₦m) | E4: Deposit % | F4: Deposit (₦m) | G4: Status | H4: SLA / commitment | I4: Backup plan | J4: Owner
A5: Flights | B5: Airline/GDS | C5: Nigeria–Kenya | D5: 66 | E5: 0.35 | F5: =D5*E5 -> 23.1 | G5: Confirmed | H5: Group seats; rebooking escalation | I5: Alternative routing/airline | J5: Travel Lead
A6: Accommodation | B6: Hotel | C6: Nairobi | D6: 41.25 | E6: 0.3 | F6: =D6*E6 -> 12.375 | G6: Confirmed | H6: 90 twin rooms; flexible rooming list | I6: Overflow hotel block | J6: Holidays Lead
A7: Ground transport | B7: Transport operator | C7: Nairobi | D7: 13.2 | E7: 0.25 | F7: =D7*E7 -> 3.3 | G7: Confirmed | H7: Buses, airport transfers, standby vehicle | I7: Secondary fleet provider | J7: Local Logistics
A8: Conference | B8: Venue & AV | C8: Nairobi | D8: 11.55 | E8: 0.4 | F8: =D8*E8 -> 4.62 | G8: Confirmed | H8: Conference hall, AV, spacing setup | I8: Hotel ballroom | J8: Events Lead
A9: Activities | B9: DMC / attractions | C9: Kenya | D9: 9.9 | E9: 0.3 | F9: =D9*E9 -> 2.97 | G9: Confirmed | H9: Timed group activities and guides | I9: Indoor alternative itinerary | J9: Holidays Lead
A10: Medical | B10: Clinic / doctor | C10: Nairobi | D10: 8.25 | E10: 0.5 | F10: =D10*E10 -> 4.125 | G10: Confirmed | H10: Standby doctor and referral pathway | I10: Partner hospital escalation | J10: Risk Lead
A11: Insurance/admin | B11: Insurer & support | C11: Nigeria/Kenya | D11: 4.95 | E11: 0.6 | F11: =D11*E11 -> 2.97 | G11: Confirmed | H11: Traveler coverage and document support | I11: Escalate to broker | J11: Account Manager

Sheet RAID Log
A1: RAID Log — Travel, Health, Financial & Supplier Risk | B1: RAID Log — Travel, Health, Financial & Supplier Risk | C1: RAID Log — Travel, Health, Financial & Supplier Risk | D1: RAID Log — Travel, Health, Financial & Supplier Risk | E1: RAID Log — Travel, Health, Financial & Supplier Risk | F1: RAID Log — Travel, Health, Financial & Supplier Risk | G1: RAID Log — Travel, Health, Financial & Supplier Risk | H1: RAID Log — Travel, Health, Financial & Supplier Risk | I1: RAID Log — Travel, Health, Financial & Supplier Risk | J1: RAID Log — Travel, Health, Financial & Supplier Risk | K1: RAID Log — Travel, Health, Financial & Supplier Risk | L1: RAID Log — Travel, Health, Financial & Supplier Risk
A2: RAID Log — Travel, Health, Financial & Supplier Risk | B2: RAID Log — Travel, Health, Financial & Supplier Risk | C2: RAID Log — Travel, Health, Financial & Supplier Risk | D2: RAID Log — Travel, Health, Financial & Supplier Risk | E2: RAID Log — Travel, Health, Financial & Supplier Risk | F2: RAID Log — Travel, Health, Financial & Supplier Risk | G2: RAID Log — Travel, Health, Financial & Supplier Risk | H2: RAID Log — Travel, Health, Financial & Supplier Risk | I2: RAID Log — Travel, Health, Financial & Supplier Risk | J2: RAID Log — Travel, Health, Financial & Supplier Risk | K2: RAID Log — Travel, Health, Financial & Supplier Risk | L2: RAID Log — Travel, Health, Financial & Supplier Risk
A3: Risk score = probability × impact. High: 15–25; Medium: 8–14; Low: 1–7. | B3: Risk score = probability × impact. High: 15–25; Medium: 8–14; Low: 1–7. | C3: Risk score = probability × impact. High: 15–25; Medium: 8–14; Low: 1–7. | D3: Risk score = probability × impact. High: 15–25; Medium: 8–14; Low: 1–7. | E3: Risk score = probability × impact. High: 15–25; Medium: 8–14; Low: 1–7. | F3: Risk score = probability × impact. High: 15–25; Medium: 8–14; Low: 1–7. | G3: Risk score = probability × impact. High: 15–25; Medium: 8–14; Low: 1–7. | H3: Risk score = probability × impact. High: 15–25; Medium: 8–14; Low: 1–7. | I3: Risk score = probability × impact. High: 15–25; Medium: 8–14; Low: 1–7. | J3: Risk score = probability × impact. High: 15–25; Medium: 8–14; Low: 1–7. | K3: Risk score = probability × impact. High: 15–25; Medium: 8–14; Low: 1–7. | L3: Risk score = probability × impact. High: 15–25; Medium: 8–14; Low: 1–7.
A4: ID | B4: Type | C4: Description | D4: Probability | E4: Impact | F4: Score | G4: Rating | H4: Response / control | I4: Owner | J4: Trigger | K4: Status | L4: Review date
A5: R-01 | B5: Risk | C5: Border, entry or testing requirements change | D5: 4 | E5: 5 | F5: =D5*E5 -> 20 | G5: =IF(F5>=15,"High",IF(F5>=8,"Medium","Low")) -> High | H5: Monitor rules; maintain document checklist; define rerouting/postponement decision gate | I5: Account Manager | J5: Policy change | K5: Mitigated | L5: 44256
A6: R-02 | B6: Risk | C6: Flight cancellation or major schedule disruption | D6: 3 | E6: 5 | F6: =D6*E6 -> 15 | G6: =IF(F6>=15,"High",IF(F6>=8,"Medium","Low")) -> High | H6: Flexible fares; backup routing; airline escalation contact; traveler regrouping plan | I6: Travel Lead | J6: Schedule change | K6: Mitigated | L6: 44256
A7: R-03 | B7: Risk | C7: Traveler illness or medical emergency | D7: 3 | E7: 5 | F7: =D7*E7 -> 15 | G7: =IF(F7>=15,"High",IF(F7>=8,"Medium","Low")) -> High | H7: Standby doctor; referral hospital; insurance; isolation and evacuation protocol | I7: Risk Lead | J7: Reported symptoms | K7: Mitigated | L7: 44260
A8: R-04 | B8: Risk | C8: Local transport supplier failure | D8: 3 | E8: 4 | F8: =D8*E8 -> 12 | G8: =IF(F8>=15,"High",IF(F8>=8,"Medium","Low")) -> Medium | H8: Backup fleet; daily vehicle checks; dispatch command channel | I8: Logistics Lead | J8: Vehicle no-show | K8: Mitigated | L8: 44260
A9: R-05 | B9: Risk | C9: Credit exposure exceeds internal limit | D9: 4 | E9: 4 | F9: =D9*E9 -> 16 | G9: =IF(F9>=15,"High",IF(F9>=8,"Medium","Low")) -> High | H9: Staged client payments; deposit calendar; weekly exposure review; approval gates | I9: Finance Lead | J9: Exposure > limit | K9: Closed | L9: 44246
A10: R-06 | B10: Risk | C10: Hotel or venue capacity constraints | D10: 3 | E10: 4 | F10: =D10*E10 -> 12 | G10: =IF(F10>=15,"High",IF(F10>=8,"Medium","Low")) -> Medium | H10: Flexible room block; overflow hotel; alternative ballroom; attrition clauses | I10: Holidays Lead | J10: Capacity reduction | K10: Mitigated | L10: 44253
A11: R-07 | B11: Risk | C11: Budget inflation or FX movement | D11: 4 | E11: 4 | F11: =D11*E11 -> 16 | G11: =IF(F11>=15,"High",IF(F11>=8,"Medium","Low")) -> High | H11: Budget rebaseline; negotiated rates; contingency reserve; variance reporting | I11: Account Manager | J11: Variance > 5% | K11: Closed | L11: 44274
A12: A-01 | B12: Assumption | C12: 180 travelers submit accurate data by cutoff | D12: 3 | E12: 3 | F12: =D12*E12 -> 9 | G12: =IF(F12>=15,"High",IF(F12>=8,"Medium","Low")) -> Medium | H12: Named coordinators; exception list; weekly readiness dashboard | I12: MRS Oil HR | J12: Readiness < 90% | K12: Validated | L12: 44253

Sheet RACI
A1: Project Governance RACI | B1: Project Governance RACI | C1: Project Governance RACI | D1: Project Governance RACI | E1: Project Governance RACI | F1: Project Governance RACI | G1: Project Governance RACI | H1: Project Governance RACI | I1: Project Governance RACI
A2: Project Governance RACI | B2: Project Governance RACI | C2: Project Governance RACI | D2: Project Governance RACI | E2: Project Governance RACI | F2: Project Governance RACI | G2: Project Governance RACI | H2: Project Governance RACI | I2: Project Governance RACI
A4: Activity | B4: Account Manager | C4: MRS Oil Sponsor | D4: Travel Consultants | E4: Finance | F4: Holidays Team | G4: Kenya Vendors | H4: Risk/Medical | I4: Traveler Coordinators
A5: Charter and requirements | B5: R/A | C5: A | D5: C | E5: C | F5: C | G5: I | H5: C | I5: C
A6: Destination and itinerary | B6: R/A | C6: C | D6: R | E6: I | F6: R | G6: C | H6: C | I6: I
A7: Flight booking | B7: A | C7: I | D7: R | E7: C | F7: I | G7: I | H7: C | I7: C
A8: Credit and payment plan | B8: R | C8: C | D8: C | E8: A/R | F8: C | G8: I | H8: I | I8: I
A9: Hotel and venue sourcing | B9: A | C9: C | D9: I | E9: C | F9: R | G9: R | H9: C | I9: I
A10: Ground transport | B10: A | C10: I | D10: I | E10: C | F10: R | G10: R | H10: C | I10: I
A11: COVID/health requirements | B11: A | C11: C | D11: C | E11: I | F11: C | G11: C | H11: R | I11: C
A12: Traveler documentation | B12: A | C12: C | D12: R | E12: I | F12: I | G12: I | H12: C | I12: R
A13: Emergency response plan | B13: A | C13: I | D13: C | E13: I | F13: C | G13: C | H13: R | I13: I
... A15: Closeout and reconciliation | B15: R/A | C15: C | D15: C | E15: R | F15: C | G15: C | H15: C | I15: I

Sheet Traveler Readiness
A1: Traveler Readiness Dashboard — Aggregate Data Only | B1: Traveler Readiness Dashboard — Aggregate Data Only | C1: Traveler Readiness Dashboard — Aggregate Data Only | D1: Traveler Readiness Dashboard — Aggregate Data Only | E1: Traveler Readiness Dashboard — Aggregate Data Only | F1: Traveler Readiness Dashboard — Aggregate Data Only | G1: Traveler Readiness Dashboard — Aggregate Data Only | H1: Traveler Readiness Dashboard — Aggregate Data Only | I1: Traveler Readiness Dashboard — Aggregate Data Only | J1: Traveler Readiness Dashboard — Aggregate Data Only
A2: Traveler Readiness Dashboard — Aggregate Data Only | B2: Traveler Readiness Dashboard — Aggregate Data Only | C2: Traveler Readiness Dashboard — Aggregate Data Only | D2: Traveler Readiness Dashboard — Aggregate Data Only | E2: Traveler Readiness Dashboard — Aggregate Data Only | F2: Traveler Readiness Dashboard — Aggregate Data Only | G2: Traveler Readiness Dashboard — Aggregate Data Only | H2: Traveler Readiness Dashboard — Aggregate Data Only | I2: Traveler Readiness Dashboard — Aggregate Data Only | J2: Traveler Readiness Dashboard — Aggregate Data Only
A3: Readiness rate = fully cleared travelers ÷ 180. | B3: Illustrative aggregate tracking avoids exposing personal traveler data. Readiness rate = fully cleared travelers ÷ 180. | C3: Illustrative aggregate tracking avoids exposing personal traveler data. Readiness rate = fully cleared travelers ÷ 180. | D3: Illustrative aggregate tracking avoids exposing personal traveler data. Readiness rate = fully cleared travelers ÷ 180. | E3: Illustrative aggregate tracking avoids exposing personal traveler data. Readiness rate = fully cleared travelers ÷ 180. | F3: Illustrative aggregate tracking avoids exposing personal traveler data. Readiness rate = fully cleared travelers ÷ 180. | G3: Illustrative aggregate tracking avoids exposing personal traveler data. Readiness rate = fully cleared travelers ÷ 180. | H3: Illustrative aggregate tracking avoids exposing personal traveler data. Readiness rate = fully cleared travelers ÷ 180. | I3: Illustrative aggregate tracking avoids exposing personal traveler data. Readiness rate = fully cleared travelers ÷ 180. | J3: Illustrative aggregate tracking avoids exposing personal traveler data. Readiness rate = fully cleared travelers ÷ 180.
A4: Checkpoint | B4: Total travelers | C4: Passport verified | D4: Ticketed | E4: Hotel assigned | F4: Health documents | G4: Briefing complete | H4: Fully cleared | I4: Readiness rate | J4: Open exceptions
A5: 8 weeks before | B5: 180 | C5: 115 | D5: 90 | E5: 70 | F5: 40 | G5: 0 | H5: 28 | I5: =H5/B5 -> 0.15555556 | J5: =B5-H5 -> 152
A6: 6 weeks before | B6: 180 | C6: 145 | D6: 130 | E6: 110 | F6: 85 | G6: 20 | H6: 72 | I6: =H6/B6 -> 0.4 | J6: =B6-H6 -> 108
A7: 4 weeks before | B7: 180 | C7: 165 | D7: 158 | E7: 150 | F7: 135 | G7: 90 | H7: 126 | I7: =H7/B7 -> 0.7 | J7: =B7-H7 -> 54
A8: 2 weeks before | B8: 180 | C8: 176 | D8: 174 | E8: 172 | F8: 168 | G8: 154 | H8: 162 | I8: =H8/B8 -> 0.9 | J8: =B8-H8 -> 18
A9: 1 week before | B9: 180 | C9: 179 | D9: 179 | E9: 178 | F9: 176 | G9: 175 | H9: 174 | I9: =H9/B9 -> 0.96666667 | J9: =B9-H9 -> 6
A10: Departure day | B10: 180 | C10: 180 | D10: 180 | E10: 180 | F10: 180 | G10: 180 | H10: 180 | I10: =H10/B10 -> 1 | J10: =B10-H10 -> 0

Sheet Executive Dashboard
A1: Executive Dashboard — MRS Oil Nairobi AGM Travel Program | B1: Executive Dashboard — MRS Oil Nairobi AGM Travel Program | C1: Executive Dashboard — MRS Oil Nairobi AGM Travel Program | D1: Executive Dashboard — MRS Oil Nairobi AGM Travel Program | E1: Executive Dashboard — MRS Oil Nairobi AGM Travel Program | F1: Executive Dashboard — MRS Oil Nairobi AGM Travel Program | G1: Executive Dashboard — MRS Oil Nairobi AGM Travel Program | H1: Executive Dashboard — MRS Oil Nairobi AGM Travel Program | I1: Executive Dashboard — MRS Oil Nairobi AGM Travel Program | J1: Executive Dashboard — MRS Oil Nairobi AGM Travel Program | K1: Executive Dashboard — MRS Oil Nairobi AGM Travel Program | L1: Executive Dashboard — MRS Oil Nairobi AGM Travel Program
A2: Executive Dashboard — MRS Oil Nairobi AGM Travel Program | B2: Executive Dashboard — MRS Oil Nairobi AGM Travel Program | C2: Executive Dashboard — MRS Oil Nairobi AGM Travel Program | D2: Executive Dashboard — MRS Oil Nairobi AGM Travel Program | E2: Executive Dashboard — MRS Oil Nairobi AGM Travel Program | F2: Executive Dashboard — MRS Oil Nairobi AGM Travel Program | G2: Executive Dashboard — MRS Oil Nairobi AGM Travel Program | H2: Executive Dashboard — MRS Oil Nairobi AGM Travel Program | I2: Executive Dashboard — MRS Oil Nairobi AGM Travel Program | J2: Executive Dashboard — MRS Oil Nairobi AGM Travel Program | K2: Executive Dashboard — MRS Oil Nairobi AGM Travel Program | L2: Executive Dashboard — MRS Oil Nairobi AGM Travel Program
A4: Travelers | B4: Travelers | C4: Revised budget | D4: Revised budget | E4: Actual spend | F4: Actual spend | G4: Budget saving | H4: Budget saving | I4: On-time movements | J4: On-time movements | K4: Satisfaction | L4: Satisfaction
A5: ='Traveler Readiness'!B10 -> 180 | C5: ='Budget Control'!C14 -> 165 | E5: ='Budget Control'!D14 -> 160.5 | G5: ='Budget Control'!F14 -> 4.5 | I5: 0.96 | K5: 0.92
A10: Metric | B10: Target | C10: Result | D10: Status | F10: TRAVELER CLEARANCE TRAJECTORY | G10: TRAVELER CLEARANCE TRAJECTORY | H10: TRAVELER CLEARANCE TRAJECTORY | I10: TRAVELER CLEARANCE TRAJECTORY | J10: TRAVELER CLEARANCE TRAJECTORY | K10: TRAVELER CLEARANCE TRAJECTORY | L10: TRAVELER CLEARANCE TRAJECTORY
A11: Fully cleared before departure | B11: 180 | C11: 180 | D11: =IF(C11>=B11,"Met","Review") -> Met | F11: 8 weeks | G11: 28 | H11: 0.156 | I11: 6 weeks | J11: 72 | K11: 0.4
A12: Manifest reconciliation | B12: 1 | C12: 1 | D12: =IF(C12>=B12,"Met","Review") -> Met | F12: 4 weeks | G12: 126 | H12: 0.7 | I12: 2 weeks | J12: 162 | K12: 0.9
A13: On-time movements | B13: 0.95 | C13: 0.96 | D13: =IF(C13>=B13,"Met","Review") -> Met | F13: 1 week | G13: 174 | H13: 0.967 | I13: Departure | J13: 180 | K13: 1
A14: Traveler satisfaction | B14: 0.9 | C14: 0.92 | D14: =IF(C14>=B14,"Met","Review") -> Met | F14: Metric | G14: Cleared | H14: Rate | I14: Metric | J14: Cleared | K14: Rate
A15: Major safety incidents | B15: 0 | C15: 0 | D15: =IF(C15>=B15,"Met","Review") -> Met | F15: Readiness gain | I15: Open exceptions
A16: Spend within revised budget | B16: 165 | C16: 160.5 | D16: =IF(C16<=B16,"Met","Review") -> Met | F16: Start to departure | G16: ='Traveler Readiness'!H10-'Traveler Readiness'!H5 -> 152 | I16: Departure day | J16: ='Traveler Readiness'!J10 -> 0 | K16: 0
A19: Closeout summary | B19: Closeout summary | C19: Closeout summary | D19: Closeout summary
A20: The program was rebaselined for pandemic-era requirements, delivered within the revised budget, and supported all 180 travelers through a structured command center, supplier controls and medical contingency plan. | B20: The program was rebaselined for pandemic-era requirements, delivered within the revised budget, and supported all 180 travelers through a structured command center, supplier controls and medical contingency plan. | C20: The program was rebaselined for pandemic-era requirements, delivered within the revised budget, and supported all 180 travelers through a structured command center, supplier controls and medical contingency plan. | D20: The program was rebaselined for pandemic-era requirements, delivered within the revised budget, and supported all 180 travelers through a structured command center, supplier controls and medical contingency plan.
A21: The program was rebaselined for pandemic-era requirements, delivered within the revised budget, and supported all 180 travelers through a structured command center, supplier controls and medical contingency plan. | B21: The program was rebaselined for pandemic-era requirements, delivered within the revised budget, and supported all 180 travelers through a structured command center, supplier controls and medical contingency plan. | C21: The program was rebaselined for pandemic-era requirements, delivered within the revised budget, and supported all 180 travelers through a structured command center, supplier controls and medical contingency plan. | D21: The program was rebaselined for pandemic-era requirements, delivered within the revised budget, and supported all 180 travelers through a structured command center, supplier controls and medical contingency plan.
A22: The program was rebaselined for pandemic-era requirements, delivered within the revised budget, and supported all 180 travelers through a structured command center, supplier controls and medical contingency plan. | B22: The program was rebaselined for pandemic-era requirements, delivered within the revised budget, and supported all 180 travelers through a structured command center, supplier controls and medical contingency plan. | C22: The program was rebaselined for pandemic-era requirements, delivered within the revised budget, and supported all 180 travelers through a structured command center, supplier controls and medical contingency plan. | D22: The program was rebaselined for pandemic-era requirements, delivered within the revised budget, and supported all 180 travelers through a structured command center, supplier controls and medical contingency plan.
A23: The program was rebaselined for pandemic-era requirements, delivered within the revised budget, and supported all 180 travelers through a structured command center, supplier controls and medical contingency plan. | B23: The program was rebaselined for pandemic-era requirements, delivered within the revised budget, and supported all 180 travelers through a structured command center, supplier controls and medical contingency plan. | C23: The program was rebaselined for pandemic-era requirements, delivered within the revised budget, and supported all 180 travelers through a structured command center, supplier controls and medical contingency plan. | D23: The program was rebaselined for pandemic-era requirements, delivered within the revised budget, and supported all 180 travelers through a structured command center, supplier controls and medical contingency plan.
A25: Checkpoint | B25: Fully cleared
A26: ='Traveler Readiness'!A5 -> 8 weeks before | B26: ='Traveler Readiness'!H5 -> 28
A27: ='Traveler Readiness'!A6 -> 6 weeks before | B27: ='Traveler Readiness'!H6 -> 72
A28: ='Traveler Readiness'!A7 -> 4 weeks before | B28: ='Traveler Readiness'!H7 -> 126
A29: ='Traveler Readiness'!A8 -> 2 weeks before | B29: ='Traveler Readiness'!H8 -> 162
A30: ='Traveler Readiness'!A9 -> 1 week before | B30: ='Traveler Readiness'!H9 -> 174
A31: ='Traveler Readiness'!A10 -> Departure day | B31: ='Traveler Readiness'!H10 -> 180
